backtesting_pp3/__init__.py
backtesting_pp3/type3.py
backtesting_pp3-0.0.1.dist-info/METADATA
backtesting_pp3-0.0.1.dist-info/WHEEL
backtesting_pp3-0.0.1.dist-info/top_level.txt
backtesting_pp3-0.0.1.dist-info/RECORD
